setup.py
ibrahim_library/__init__.py
ibrahim_library/ibrahim.py
ibrahim_library/test_1.py
ibrahim_library/test_2.py
ibrahim_library.egg-info/PKG-INFO
ibrahim_library.egg-info/SOURCES.txt
ibrahim_library.egg-info/dependency_links.txt
ibrahim_library.egg-info/top_level.txt