Metadata-Version: 2.1
Name: ibrahim-library
Version: 0.2.0
Summary: Berechnung von ACCF & ERRE
Author: Ibrahim
License: MIT
